adsb/__init__.py
adsb/adsb.py
adsb/crc.py
adsb/helpers.py
adsb/tracker.py
pyadsb-0.0.3.dist-info/METADATA
pyadsb-0.0.3.dist-info/WHEEL
pyadsb-0.0.3.dist-info/top_level.txt
pyadsb-0.0.3.dist-info/RECORD
