Metadata-Version: 2.1
Name: pyadsb
Version: 0.0.3
Summary: Functionality for encoding/decoding ADSB messages written in pure Python 3
Home-page: https://github.com/enok71/adsb
Author: Oskar Enoksson
Author-email: Oskar Enoksson <enok@lysator.liu.se>
Maintainer-email: Oskar Enoksson <enok@lysator.liu.se>
Project-URL: Homepage, https://github.com/enok71/adsb
Project-URL: Issues, https://github.com/enok71/adsb/issues
Project-URL: Documentation, https://github.com/enok71/adsb/wiki
Keywords: adsb,ads-b,aircraft,mode-s
Classifier: Programming Language :: Python :: 3
Classifier: License :: OSI Approved :: MIT License
Classifier: Operating System :: OS Independent
Classifier: Programming Language :: Python :: 3.8
Classifier: Topic :: Software Development :: Libraries :: Python Modules
Classifier: Development Status :: 3 - Alpha
Requires-Python: >=3.8
